canisterpy/__init__.py
canisterpy/canister.py
canisterpy/errors.py
canisterpy/types.py
cnstr-1.0.2.dist-info/LICENSE
cnstr-1.0.2.dist-info/METADATA
cnstr-1.0.2.dist-info/WHEEL
cnstr-1.0.2.dist-info/top_level.txt
cnstr-1.0.2.dist-info/RECORD
