Metadata-Version: 2.1
Name: cnstr
Version: 1.0.2
Summary: A simple, easy-to-use API wrapper for https://canister.me.
Home-page: https://github.com/cnstr/canister.py
Author: Canister
Author-email: support@canister.me
License: UNKNOWN
Project-URL: Bug Tracker, https://github.com/cnstr/canister.py/issues
Platform: UNKNOWN
Classifier: Programming Language :: Python :: 3
Classifier: License :: OSI Approved :: Apache Software License
Classifier: Operating System :: OS Independent
Requires-Python: >=3.6
License-File: LICENSE
Requires-Dist: aiocache
Requires-Dist: aiohttp
Requires-Dist: ujson
Requires-Dist: msgpack
